soners
