Metadata-Version: 1.1
Name: soners
Version: 1.0.7
Summary: PySerial reader extension for Tornado
Home-page: https://github.com/cpapazaf/soners
Author: Christos Papazafeiropoulos
Author-email: xpapazaf@gmail.com
License: Apache License
Platform: any
Classifier: License :: OSI Approved :: Apache Software License
Classifier: Programming Language :: Python :: 3.4
Classifier: Programming Language :: Python :: 3.5
Classifier: Programming Language :: Python :: Implementation :: CPython
Classifier: Programming Language :: Python :: Implementation :: PyPy
